wv_store/__init__.py
wv_store/cli.py
wv_store/main.py
wv_store-0.1.dist-info/METADATA
wv_store-0.1.dist-info/WHEEL
wv_store-0.1.dist-info/entry_points.txt
wv_store-0.1.dist-info/top_level.txt
wv_store-0.1.dist-info/RECORD
